[{"YEAR_LEVEL":3,"CALENDAR_YEAR":2008,"MEAN":389.5583333333},{"YEAR_LEVEL":3,"CALENDAR_YEAR":2009,"MEAN":395.8861111111},{"YEAR_LEVEL":3,"CALENDAR_YEAR":2010,"MEAN":395.0111111111},{"YEAR_LEVEL":3,"CALENDAR_YEAR":2011,"MEAN":399.7333333333},{"YEAR_LEVEL":3,"CALENDAR_YEAR":2012,"MEAN":402.6955555556},{"YEAR_LEVEL":3,"CALENDAR_YEAR":2013,"MEAN":403.5355555556},{"YEAR_LEVEL":3,"CALENDAR_YEAR":2014,"MEAN":400.94},{"YEAR_LEVEL":3,"CALENDAR_YEAR":2015,"MEAN":405.0555555556},{"YEAR_LEVEL":3,"CALENDAR_YEAR":2016,"MEAN":410.28},{"YEAR_LEVEL":3,"CALENDAR_YEAR":2017,"MEAN":409.6533333333},{"YEAR_LEVEL":3,"CALENDAR_YEAR":2018,"MEAN":406.8311111111},{"YEAR_LEVEL":3,"CALENDAR_YEAR":2019,"MEAN":412.2688888889},{"YEAR_LEVEL":3,"CALENDAR_YEAR":2021,"MEAN":412.3955555556},{"YEAR_LEVEL":3,"CALENDAR_YEAR":2022,"MEAN":412.0},{"YEAR_LEVEL":5,"CALENDAR_YEAR":2008,"MEAN":474.8027777778},{"YEAR_LEVEL":5,"CALENDAR_YEAR":2009,"MEAN":481.95},{"YEAR_LEVEL":5,"CALENDAR_YEAR":2010,"MEAN":480.2333333333},{"YEAR_LEVEL":5,"CALENDAR_YEAR":2011,"MEAN":477.88},{"YEAR_LEVEL":5,"CALENDAR_YEAR":2012,"MEAN":478.1022222222},{"YEAR_LEVEL":5,"CALENDAR_YEAR":2013,"MEAN":482.0866666667},{"YEAR_LEVEL":5,"CALENDAR_YEAR":2014,"MEAN":481.7711111111},{"YEAR_LEVEL":5,"CALENDAR_YEAR":2015,"MEAN":484.06},{"YEAR_LEVEL":5,"CALENDAR_YEAR":2016,"MEAN":483.64},{"YEAR_LEVEL":5,"CALENDAR_YEAR":2017,"MEAN":484.4888888889},{"YEAR_LEVEL":5,"CALENDAR_YEAR":2018,"MEAN":484.1155555556},{"YEAR_LEVEL":5,"CALENDAR_YEAR":2019,"MEAN":484.1666666667},{"YEAR_LEVEL":5,"CALENDAR_YEAR":2021,"MEAN":487.6844444444},{"YEAR_LEVEL":5,"CALENDAR_YEAR":2022,"MEAN":488.3333333333},{"YEAR_LEVEL":7,"CALENDAR_YEAR":2008,"MEAN":529.025},{"YEAR_LEVEL":7,"CALENDAR_YEAR":2009,"MEAN":532.4166666667},{"YEAR_LEVEL":7,"CALENDAR_YEAR":2010,"MEAN":535.5777777778},{"YEAR_LEVEL":7,"CALENDAR_YEAR":2011,"MEAN":528.64},{"YEAR_LEVEL":7,"CALENDAR_YEAR":2012,"MEAN":528.8311111111},{"YEAR_LEVEL":7,"CALENDAR_YEAR":2013,"MEAN":527.3488888889},{"YEAR_LEVEL":7,"CALENDAR_YEAR":2014,"MEAN":529.8622222222},{"YEAR_LEVEL":7,"CALENDAR_YEAR":2015,"MEAN":528.1222222222},{"YEAR_LEVEL":7,"CALENDAR_YEAR":2016,"MEAN":529.3622222222},{"YEAR_LEVEL":7,"CALENDAR_YEAR":2017,"MEAN":531.2066666667},{"YEAR_LEVEL":7,"CALENDAR_YEAR":2018,"MEAN":528.5066666667},{"YEAR_LEVEL":7,"CALENDAR_YEAR":2019,"MEAN":531.0733333333},{"YEAR_LEVEL":7,"CALENDAR_YEAR":2021,"MEAN":529.5311111111},{"YEAR_LEVEL":7,"CALENDAR_YEAR":2022,"MEAN":530.6222222222},{"YEAR_LEVEL":9,"CALENDAR_YEAR":2008,"MEAN":569.4944444444},{"YEAR_LEVEL":9,"CALENDAR_YEAR":2009,"MEAN":572.9111111111},{"YEAR_LEVEL":9,"CALENDAR_YEAR":2010,"MEAN":571.825},{"YEAR_LEVEL":9,"CALENDAR_YEAR":2011,"MEAN":568.4933333333},{"YEAR_LEVEL":9,"CALENDAR_YEAR":2012,"MEAN":564.9955555556},{"YEAR_LEVEL":9,"CALENDAR_YEAR":2013,"MEAN":567.0533333333},{"YEAR_LEVEL":9,"CALENDAR_YEAR":2014,"MEAN":566.8311111111},{"YEAR_LEVEL":9,"CALENDAR_YEAR":2015,"MEAN":565.5022222222},{"YEAR_LEVEL":9,"CALENDAR_YEAR":2016,"MEAN":566.5288888889},{"YEAR_LEVEL":9,"CALENDAR_YEAR":2017,"MEAN":566.4977777778},{"YEAR_LEVEL":9,"CALENDAR_YEAR":2018,"MEAN":567.8777777778},{"YEAR_LEVEL":9,"CALENDAR_YEAR":2019,"MEAN":567.04},{"YEAR_LEVEL":9,"CALENDAR_YEAR":2021,"MEAN":565.1755555556},{"YEAR_LEVEL":9,"CALENDAR_YEAR":2022,"MEAN":566.9288888889}]